macmac/__init__.py
macmac-0.1.dist-info/METADATA
macmac-0.1.dist-info/WHEEL
macmac-0.1.dist-info/top_level.txt
macmac-0.1.dist-info/RECORD
