Metadata-Version: 2.1
Name: macmac
Version: 0.1
Summary: Testing how python packages actually work
Home-page: http://github.com/dan/showme
Author: Flying Circus
Author-email: flyingcircus@example.com
License: MIT
Platform: UNKNOWN
